rtl/spi_define.v
`define SPI_DIVIDER_LEN 16 //thus divider value can be from 0 to 65535
`define SPI_MAX_CHARS 128 //Maximum 128 bits can be transferred in single transaction
`define SPI_SS_MAX 32 //Maximum number of Slave Signals

rtl/clk_gen.v
//====================================================
// Project     : RTL to GDS of SPI Protocol
// Author      : Agnibha Sarkar
//
// Revision    : v1.0
// Last Updated: 23-06-2026
//
// Changes: None
//====================================================


`include "spi_define.v"

//The arithmatic it SPI_clk = (SYS_clk)/ (2 * (divider + 1));
module clk_gen(input clk_sys, reset, enable, last_clk, go, input [`SPI_DIVIDER_LEN-1:0] divider, output reg clk_out, pos_edge, neg_edge);

reg [`SPI_DIVIDER_LEN-1:0] counter; //Counter Register
wire cnt_zero; // Active high when Counter is 0;
wire cnt_one;

assign cnt_zero = counter == 0;
assign cnt_one = counter == 1;

//half period counter count (Down counter)
always @(posedge clk_sys or posedge reset) begin
    if(reset)
        counter <= {`SPI_DIVIDER_LEN{1'b1}}; //All 1s (safe choice)
    else if (!enable || cnt_zero)
        counter <= divider; //If not enabled or counter is 0, keep loading it with divider value
    else
        counter <= counter - 1'b1; //Count down by 1
end

//SCLK, posedge and negedge generation
always @(posedge clk_sys or posedge reset) begin
    if(reset) begin
        clk_out <= 1'b0; //CPOL = 0 
        pos_edge <= 1'b0;
        neg_edge <= 1'b0;
    end
    else begin
        //Since CPOL = 0, after the last clock, we check if its 1, then toggle
        //else if its 0, then dont toggle
        clk_out <= (enable && cnt_zero && (!last_clk || clk_out)) ? ~clk_out : clk_out;
        pos_edge  <= (enable && !clk_out && cnt_one) || (!(|divider) && clk_out) || (!(|divider) && go && !enable);
        neg_edge  <= (enable && clk_out && cnt_one) || (!(|divider) && !clk_out && enable);
    end
end

endmodule

testbench/clk_gen_tb.v
`timescale 1ns/1ps

`include "spi_define.v"

module spi_clgen_tb;

reg clk_in;
reg rst;
reg go;
reg enable;
reg last_clk;

reg [`SPI_DIVIDER_LEN-1:0] divider;

wire clk_out;
wire pos_edge;
wire neg_edge;


// DUT
clk_gen dut(

    .clk_sys(clk_in),
    .reset(rst),
    .go(go),
    .enable(enable),
    .last_clk(last_clk),
    .divider(divider),

    .clk_out(clk_out),
    .pos_edge(pos_edge),
    .neg_edge(neg_edge)

);


// Clock generation

initial begin

    clk_in = 0;

    forever #5 clk_in = ~clk_in;      // 10 ns period

end



// Dump waveform

initial begin

    $dumpfile("spi_clgen.vcd");

    $dumpvars(0, spi_clgen_tb);

end



// Monitor

initial begin

$monitor(

"T=%0t rst=%0b en=%0b go=%0b last=%0b div=%0d | cnt=%0d clk_out=%0b pos=%0b neg=%0b",

$time,

rst,

enable,

go,

last_clk,

divider,

dut.counter,

clk_out,

pos_edge,

neg_edge

);

end




// Stimulus

initial begin

    // Initial values

    rst      = 1;

    enable   = 0;

    go       = 0;

    last_clk = 0;

    divider  = 0;


    //-----------------------

    // RESET

    //-----------------------

    #30;

    rst = 0;


    //-----------------------

    // divider = 4 test

    //-----------------------

    divider = 4;

    enable  = 0;

    #20;


    enable = 1;


    // Run for a while

    #250;


    //-----------------------

    // Last clock

    //-----------------------

    last_clk = 1;


    #80;


    enable   = 0;

    last_clk = 0;


    #40;


    //-----------------------

    // divider=0 test

    //-----------------------

    divider = 0;

    enable  = 0;


    #10;

    go = 1;


    #10;

    go = 0;


    enable = 1;


    #120;


    enable = 0;


    #40;


    $finish;

end


endmodule

testbench/spi_clgen.vcd
$date
	Tue Jun 23 19:33:07 2026
$end
$version
	Icarus Verilog
$end
$timescale
	1ps
$end
$scope module spi_clgen_tb $end
$var wire 1 ! pos_edge $end
$var wire 1 " neg_edge $end
$var wire 1 # clk_out $end
$var reg 1 $ clk_in $end
$var reg 16 % divider [15:0] $end
$var reg 1 & enable $end
$var reg 1 ' go $end
$var reg 1 ( last_clk $end
$var reg 1 ) rst $end
$scope module dut $end
$var wire 1 $ clk_sys $end
$var wire 16 * divider [15:0] $end
$var wire 1 & enable $end
$var wire 1 ' go $end
$var wire 1 ( last_clk $end
$var wire 1 ) reset $end
$var wire 1 + cnt_zero $end
$var wire 1 , cnt_one $end
$var reg 1 # clk_out $end
$var reg 16 - counter [15:0] $end
$var reg 1 " neg_edge $end
$var reg 1 ! pos_edge $end
$upscope $end
$upscope $end
$enddefinitions $end
#0
$dumpvars
b1111111111111111 -
0,
0+
b0 *
1)
0(
0'
0&
b0 %
0$
0#
0"
0!
$end
#5000
1$
#10000
0$
#15000
1$
#20000
0$
#25000
1$
#30000
0$
b100 %
b100 *
0)
#35000
b100 -
1$
#40000
0$
#45000
1$
#50000
0$
1&
#55000
b11 -
1$
#60000
0$
#65000
b10 -
1$
#70000
0$
#75000
1,
b1 -
1$
#80000
0$
#85000
1!
1+
0,
b0 -
1$
#90000
0$
#95000
0+
b100 -
0!
1#
1$
#100000
0$
#105000
b11 -
1$
#110000
0$
#115000
b10 -
1$
#120000
0$
#125000
1,
b1 -
1$
#130000
0$
#135000
1+
0,
b0 -
1"
1$
#140000
0$
#145000
0"
0#
0+
b100 -
1$
#150000
0$
#155000
b11 -
1$
#160000
0$
#165000
b10 -
1$
#170000
0$
#175000
1,
b1 -
1$
#180000
0$
#185000
1!
1+
0,
b0 -
1$
#190000
0$
#195000
0+
b100 -
0!
1#
1$
#200000
0$
#205000
b11 -
1$
#210000
0$
#215000
b10 -
1$
#220000
0$
#225000
1,
b1 -
1$
#230000
0$
#235000
1+
0,
b0 -
1"
1$
#240000
0$
#245000
0"
0#
0+
b100 -
1$
#250000
0$
#255000
b11 -
1$
#260000
0$
#265000
b10 -
1$
#270000
0$
#275000
1,
b1 -
1$
#280000
0$
#285000
1!
1+
0,
b0 -
1$
#290000
0$
#295000
0+
b100 -
0!
1#
1$
#300000
0$
1(
#305000
b11 -
1$
#310000
0$
#315000
b10 -
1$
#320000
0$
#325000
1,
b1 -
1$
#330000
0$
#335000
1+
0,
b0 -
1"
1$
#340000
0$
#345000
0"
0#
0+
b100 -
1$
#350000
0$
#355000
b11 -
1$
#360000
0$
#365000
b10 -
1$
#370000
0$
#375000
1,
b1 -
1$
#380000
0$
0(
0&
#385000
0,
b100 -
1$
#390000
0$
#395000
1$
#400000
0$
#405000
1$
#410000
0$
#415000
1$
#420000
0$
b0 %
b0 *
#425000
1+
b0 -
1$
#430000
0$
1'
#435000
1!
1$
#440000
0$
1&
0'
#445000
1"
0!
1#
1$
#450000
0$
#455000
0"
1!
0#
1$
#460000
0$
#465000
1"
0!
1#
1$
#470000
0$
#475000
0"
1!
0#
1$
#480000
0$
#485000
1"
0!
1#
1$
#490000
0$
#495000
0"
1!
0#
1$
#500000
0$
#505000
1"
0!
1#
1$
#510000
0$
#515000
0"
1!
0#
1$
#520000
0$
#525000
1"
0!
1#
1$
#530000
0$
#535000
0"
1!
0#
1$
#540000
0$
#545000
1"
0!
1#
1$
#550000
0$
#555000
0"
1!
0#
1$
#560000
0$
0&
#565000
0!
1$
